poetry_demo_said/__init__.py
poetry_demo_said-0.1.0.dist-info/WHEEL
poetry_demo_said-0.1.0.dist-info/METADATA
poetry_demo_said-0.1.0.dist-info/RECORD
