Metadata-Version: 2.1
Name: poetry-demo-said
Version: 0.1.0
Summary: 
Author: said
Author-email: albertadine760@gmail.com
Requires-Python: >=3.9,<4.0
Classifier: Programming Language :: Python :: 3
Classifier: Programming Language :: Python :: 3.9
Requires-Dist: requests (>=2.25.1,<3.0.0)
